{"date":"2026-06-26","generated_at":"2026-06-26T02:15:01.697Z","a_stock":{"indices":{"sh000001":{"name":"上证指数","close":3356.32,"change_pct":0.42},"sz399001":{"name":"深证成指","close":10842.17,"change_pct":-0.35},"sz399006":{"name":"创业板指","close":2215.63,"change_pct":0.18},"sh000688":{"name":"科创50","close":958.41,"change_pct":1.25}},"volume":"8500亿"},"capital":{"northbound":{"net_flow":23.5,"confidence":"✅"},"margin":{"balance":15230,"confidence":"✅"}},"us_stock":{"indices":{"djia":{"close":42830.5,"change_pct":-0.52},"nasdaq":{"close":19320.8,"change_pct":0.38},"sp500":{"close":5872.3,"change_pct":-0.15}}},"forex_commodity":{"usd_index":104.2,"usdcnh":7.18},"data_sources":{},"news_events":[]}